qka/__init__.py
qka/brokers/__init__.py
qka/brokers/client.py
qka/brokers/server.py
qka/brokers/trade.py
qka/core/__init__.py
qka/core/backtest.py
qka/core/config.py
qka/core/events.py
qka/core/plot.py
qka/core/data/__init__.py
qka/core/data/akshare.py
qka/core/data/base.py
qka/core/data/qmt.py
qka/mcp/__init__.py
qka/mcp/api.py
qka/mcp/server.py
qka/utils/__init__.py
qka/utils/anis.py
qka/utils/logger.py
qka/utils/tools.py
qka/utils/util.py
qka-1.0.4.dist-info/METADATA
qka-1.0.4.dist-info/WHEEL
qka-1.0.4.dist-info/licenses/LICENSE
qka-1.0.4.dist-info/RECORD
