Metadata-Version: 2.4
Name: qka
Version: 1.0.4
Summary: 快捷量化助手（Quick Quantitative Assistant）- 简洁易用的A股量化交易框架
Project-URL: Home, https://github.com/zsrl/qka
Project-URL: Documentation, https://zsrl.github.io/qka
Project-URL: Repository, https://github.com/zsrl/qka
Project-URL: Issues, https://github.com/zsrl/qka/issues
Author-email: myc <mayuanchi1029@gmail.com>
License: MIT License
License-File: LICENSE
Classifier: License :: OSI Approved :: MIT License
Classifier: Programming Language :: Python :: 3
Classifier: Programming Language :: Python :: 3.10
Classifier: Programming Language :: Python :: 3.11
Classifier: Programming Language :: Python :: 3.12
Requires-Python: >=3.10
Requires-Dist: akshare>=1.16.93
Requires-Dist: fastapi>=0.115.13
Requires-Dist: flask>=3.1.1
Requires-Dist: ipykernel>=6.29.5
Requires-Dist: mcp[cli]>=1.9.0
Requires-Dist: nbformat>=5.10.4
Requires-Dist: plotly>=6.1.1
Requires-Dist: uvicorn>=0.34.3
Requires-Dist: xtquant>=241014.1.2
Provides-Extra: dev
Requires-Dist: hatch-vcs>=0.3.0; extra == 'dev'
Requires-Dist: mkdocs-material>=9.6.14; extra == 'dev'
Requires-Dist: mkdocs>=1.6.1; extra == 'dev'
Requires-Dist: mkdocstrings-python>=1.16.12; extra == 'dev'
Requires-Dist: mkdocstrings>=0.29.1; extra == 'dev'
Requires-Dist: pytest-cov>=4.0.0; extra == 'dev'
Requires-Dist: pytest>=7.0.0; extra == 'dev'
Requires-Dist: python-semantic-release>=9.0.0; extra == 'dev'
